checkpointing/__init__.py
checkpointing/_typing.py
checkpointing/config.py
checkpointing/exceptions.py
checkpointing/cache/__init__.py
checkpointing/cache/base.py
checkpointing/cache/in_mem_lru.py
checkpointing/cache/pickle_file.py
checkpointing/decorator/__init__.py
checkpointing/decorator/base.py
checkpointing/decorator/default.py
checkpointing/hash/__init__.py
checkpointing/hash/generic.py
checkpointing/hash/stream.py
checkpointing/identifier/__init__.py
checkpointing/identifier/func_call/__init__.py
checkpointing/identifier/func_call/auto.py
checkpointing/identifier/func_call/base.py
checkpointing/identifier/func_call/context.py
checkpointing/logging/__init__.py
checkpointing/refactor/__init__.py
checkpointing/refactor/funcdef.py
checkpointing/refactor/util.py
checkpointing/util/__init__.py
checkpointing/util/pickle.py
checkpointing/util/timing.py
checkpointing-1.0.1.dist-info/LICENSE
checkpointing-1.0.1.dist-info/METADATA
checkpointing-1.0.1.dist-info/WHEEL
checkpointing-1.0.1.dist-info/top_level.txt
checkpointing-1.0.1.dist-info/RECORD
