Metadata-Version: 2.1
Name: checkpointing
Version: 1.0.1
Summary: Persistent cache for Python functions
Home-page: https://github.com/Vopaaz/checkpointing
Author: Vopaaz
Author-email: liyifan945@gmail.com
Classifier: Programming Language :: Python :: 3.8
Classifier: Programming Language :: Python :: 3.9
Classifier: Programming Language :: Python :: 3.10
Classifier: Programming Language :: Python :: 3.11
Classifier: Programming Language :: Python :: 3.12
Classifier: License :: OSI Approved :: MIT License
Requires-Python: >=3.8, <=3.12
License-File: LICENSE
Requires-Dist: dill>=0.3.5
